aq/options.py
aq/price.py
aq/util.py
alphaquery_sdk-0.1.0.dist-info/METADATA
alphaquery_sdk-0.1.0.dist-info/WHEEL
alphaquery_sdk-0.1.0.dist-info/top_level.txt
alphaquery_sdk-0.1.0.dist-info/RECORD
