Metadata-Version: 2.1
Name: alphaquery-sdk
Version: 0.1.0
Summary: AlphaQuery SDK
Requires-Dist: pandas
Requires-Dist: requests
